ucpify/__init__.py
ucpify/app.py
ucpify/cli.py
ucpify/config.py
ucpify/db.py
ucpify/logger.py
ucpify/paypal_payment.py
ucpify/schema.py
ucpify/server.py
ucpify/server_db.py
ucpify/stripe_payment.py
ucpify-1.0.1.dist-info/METADATA
ucpify-1.0.1.dist-info/WHEEL
ucpify-1.0.1.dist-info/entry_points.txt
ucpify-1.0.1.dist-info/top_level.txt
ucpify-1.0.1.dist-info/RECORD
