Metadata-Version: 2.4
Name: ucpify
Version: 1.0.1
Summary: Generate UCP-compliant servers for merchants from a simple schema
License: MIT
Project-URL: Homepage, https://ucp.dev
Project-URL: Repository, https://github.com/hemanth/ucpify
Keywords: ucp,commerce,checkout,agentic,ai-commerce
Classifier: Development Status :: 4 - Beta
Classifier: Intended Audience :: Developers
Classifier: License :: OSI Approved :: MIT License
Classifier: Programming Language :: Python :: 3
Classifier: Programming Language :: Python :: 3.9
Classifier: Programming Language :: Python :: 3.10
Classifier: Programming Language :: Python :: 3.11
Classifier: Programming Language :: Python :: 3.12
Requires-Python: >=3.9
Requires-Dist: flask>=3.0.0
Requires-Dist: pydantic>=2.0.0
Requires-Dist: click>=8.0.0
Requires-Dist: python-dotenv>=1.0.0
Requires-Dist: structlog>=24.0.0
Requires-Dist: stripe>=7.0.0
Requires-Dist: paypalserversdk>=1.0.0
Provides-Extra: dev
Requires-Dist: pytest>=8.0.0; extra == "dev"
Requires-Dist: pytest-flask>=1.3.0; extra == "dev"
